livesatproto-0.2.1.dist-info/METADATA
livesatproto-0.2.1.dist-info/WHEEL
livesatproto-0.2.1.dist-info/entry_points.txt
livesatproto-0.2.1.dist-info/licenses/LICENSE
livesatproto/__init__.py
livesatproto/where_now.py
livesatproto-0.2.1.dist-info/RECORD
