Metadata-Version: 2.1
Name: LiveSatProto
Version: 0.2.1
Summary: Prototype for tracking real-time satellite positions in orbit.
Author-Email: ppabam <tom@diginori.com>
License: GPL-3.0 license
Project-URL: Homepage, https://github.com/sunsin-shop/LiveSatProto
Project-URL: Issues, https://github.com/sunsin-shop/LiveSatProto/issues
Requires-Python: >=3.10
Requires-Dist: typer>=0.15.1
